setup.py
mul_r/__init__.py
mul_r/operation.py
mul_r.egg-info/PKG-INFO
mul_r.egg-info/SOURCES.txt
mul_r.egg-info/dependency_links.txt
mul_r.egg-info/not-zip-safe
mul_r.egg-info/top_level.txt