Metadata-Version: 2.1
Name: mul_r
Version: 0.1
Summary: Multiplication of two numbers
Author-email: nilabjaroy5@gmail.com
